autogen_ext_mcp/tools/__init__.py
autogen_ext_mcp/tools/adapter.py
autogen_ext_mcp/tools/toolkit.py
autogen_ext_mcp-0.2.2.dist-info/METADATA
autogen_ext_mcp-0.2.2.dist-info/WHEEL
autogen_ext_mcp-0.2.2.dist-info/licenses/LICENSE
autogen_ext_mcp-0.2.2.dist-info/RECORD
