Metadata-Version: 2.4
Name: autogen-ext-mcp
Version: 0.2.2
Summary: MCP Tools extension for AutoGen >= v0.4
Project-URL: homepage, https://github.com/richard-gyiko/autogen-ext-mcp
Project-URL: Documentation, https://github.com/richard-gyiko/autogen-ext-mcp#readme
Project-URL: Repository, https://github.com/richard-gyiko/autogen-ext-mcp.git
Project-URL: Bug-Tracker, https://github.com/richard-gyiko/autogen-ext-mcp/issues
Author-email: Richard Gyiko <gyiko.richard@outlook.com>
License-Expression: MIT
License-File: LICENSE
Keywords: ai,autogen,autogen-ext,integration,model-context-protocol,tools
Classifier: Development Status :: 4 - Beta
Classifier: Intended Audience :: Developers
Classifier: License :: OSI Approved :: MIT License
Classifier: Programming Language :: Python :: 3
Classifier: Programming Language :: Python :: 3.10
Classifier: Programming Language :: Python :: 3.11
Classifier: Programming Language :: Python :: 3.12
Classifier: Topic :: Scientific/Engineering :: Artificial Intelligence
Classifier: Topic :: Software Development :: Libraries :: Python Modules
Classifier: Typing :: Typed
Requires-Python: >=3.10
Requires-Dist: autogen-core<0.5,>=0.4.2
Requires-Dist: json-schema-to-pydantic>=0.2.0
Requires-Dist: mcp>=1.1.2
Provides-Extra: samples
Requires-Dist: autogen-agentchat<0.5,>=0.4.2; extra == 'samples'
Requires-Dist: autogen-ext[azure,openai]<0.5,>=0.4.2; extra == 'samples'
Requires-Dist: python-dotenv>=1.0.1; extra == 'samples'
Requires-Dist: rich>=13.9.4; extra == 'samples'
